{
  "0": { "L": 0.3487, "M": 3.3464, "S": 0.14602 },
  "1": { "L": 0.3487, "M": 3.3627, "S": 0.14558 },
  "2": { "L": 0.3487, "M": 3.3790, "S": 0.14514 },
  "3": { "L": 0.3487, "M": 3.3952, "S": 0.14470 },
  "7": { "L": 0.3487, "M": 3.4776, "S": 0.14282 },
  "14": { "L": 0.3487, "M": 3.5999, "S": 0.13952 },
  "30": { "L": 0.3487, "M": 3.8598, "S": 0.13219 },
  "60": { "L": 0.2297, "M": 4.4709, "S": 0.12574 },
  "90": { "L": 0.1970, "M": 4.9950, "S": 0.12385 },
  "120": { "L": 0.1738, "M": 5.4458, "S": 0.12341 },
  "150": { "L": 0.1553, "M": 5.8376, "S": 0.12378 },
  "180": { "L": 0.1395, "M": 6.1759, "S": 0.12465 },
  "210": { "L": 0.1257, "M": 6.4750, "S": 0.12578 },
  "240": { "L": 0.1134, "M": 6.7488, "S": 0.12703 },
  "270": { "L": 0.1021, "M": 7.0023, "S": 0.12831 },
  "300": { "L": 0.0917, "M": 7.2388, "S": 0.12959 },
  "330": { "L": 0.0820, "M": 7.4607, "S": 0.13084 },
  "365": { "L": 0.0714, "M": 7.7049, "S": 0.13229 }
}
